[{"word": "Jalp-a", "c_deletion": "Jala", "l_deletion": "Japa", "pot1": "Jal*a", "pot2": "Jap*a"}, {"word": "Jalp-acici", "c_deletion": "Jalacici", "l_deletion": "Japacici", "pot1": "Jal*acici", "pot2": "Jap*acici"}, {"word": "Jalp-aciko", "c_deletion": "Jalaciko", "l_deletion": "Japaciko", "pot1": "Jal*aciko", "pot2": "Jap*aciko"}, {"word": "Jalp-aciniga", "c_deletion": "Jalaciniga", "l_deletion": "Japaciniga", "pot1": "Jal*aciniga", "pot2": "Jap*aciniga"}, {"word": "Jalp-acinxn", "c_deletion": "Jalacinxn", "l_deletion": "Japacinxn", "pot1": "Jal*acinxn", "pot2": "Jap*acinxn"}, {"word": "Jalp-acinxnteyo", "c_deletion": "Jalacinxnteyo", "l_deletion": "Japacinxnteyo", "pot1": "Jal*acinxnteyo", "pot2": "Jap*acinxnteyo"}, {"word": "Jalp-acin", "c_deletion": "Jalacin", "l_deletion": "Japacin", "pot1": "Jal*acin", "pot2": "Jap*acin"}, {"word": "Jalp-acintanxn", "c_deletion": "Jalacintanxn", "l_deletion": "Japacintanxn", "pot1": "Jal*acintanxn", "pot2": "Jap*acintanxn"}, {"word": "Jalp-acintatxnci", "c_deletion": "Jalacintatxnci", "l_deletion": "Japacintatxnci", "pot1": "Jal*acintatxnci", "pot2": "Jap*acintatxnci"}, {"word": "Jalp-acyv", "c_deletion": "Jalacyv", "l_deletion": "Japacyv", "pot1": "Jal*acyv", "pot2": "Jap*acyv"}, {"word": "Jalp-acyvkaciko", "c_deletion": "Jalacyvkaciko", "l_deletion": "Japacyvkaciko", "pot1": "Jal*acyvkaciko", "pot2": "Jap*acyvkaciko"}, {"word": "Jalp-acyvsv", "c_deletion": "Jalacyvsv", "l_deletion": "Japacyvsv", "pot1": "Jal*acyvsv", "pot2": "Jap*acyvsv"}, {"word": "Jalp-acyvSkunalanxn", "c_deletion": "JalacyvSkunalanxn", "l_deletion": "JapacyvSkunalanxn", "pot1": "Jal*acyvSkunalanxn", "pot2": "Jap*acyvSkunalanxn"}, {"word": "Jalp-acyvSnxnte", "c_deletion": "JalacyvSnxnte", "l_deletion": "JapacyvSnxnte", "pot1": "Jal*acyvSnxnte", "pot2": "Jap*acyvSnxnte"}, {"word": "Jalp-acyvSta", "c_deletion": "JalacyvSta", "l_deletion": "JapacyvSta", "pot1": "Jal*acyvSta", "pot2": "Jap*acyvSta"}, {"word": "Jalp-acyvStako", "c_deletion": "JalacyvStako", "l_deletion": "JapacyvStako", "pot1": "Jal*acyvStako", "pot2": "Jap*acyvStako"}, {"word": "Jalp-acyvStanxn", "c_deletion": "JalacyvStanxn", "l_deletion": "JapacyvStanxn", "pot1": "Jal*acyvStanxn", "pot2": "Jap*acyvStanxn"}, {"word": "Jalp-acyvSxmyvn", "c_deletion": "JalacyvSxmyvn", "l_deletion": "JapacyvSxmyvn", "pot1": "Jal*acyvSxmyvn", "pot2": "Jap*acyvSxmyvn"}, {"word": "Jalp-akaciko", "c_deletion": "Jalakaciko", "l_deletion": "Japakaciko", "pot1": "Jal*akaciko", "pot2": "Jap*akaciko"}, {"word": "Jalp-asv", "c_deletion": "Jalasv", "l_deletion": "Japasv", "pot1": "Jal*asv", "pot2": "Jap*asv"}, {"word": "Jalp-ato", "c_deletion": "Jalato", "l_deletion": "Japato", "pot1": "Jal*ato", "pot2": "Jap*ato"}, {"word": "Jalp-ayo", "c_deletion": "Jalayo", "l_deletion": "Japayo", "pot1": "Jal*ayo", "pot2": "Jap*ayo"}, {"word": "Jalp-aSki", "c_deletion": "JalaSki", "l_deletion": "JapaSki", "pot1": "Jal*aSki", "pot2": "Jap*aSki"}, {"word": "Jalp-aSkvtxnyo", "c_deletion": "JalaSkvtxnyo", "l_deletion": "JapaSkvtxnyo", "pot1": "Jal*aSkvtxnyo", "pot2": "Jap*aSkvtxnyo"}, {"word": "Jalp-aSnxnte", "c_deletion": "JalaSnxnte", "l_deletion": "JapaSnxnte", "pot1": "Jal*aSnxnte", "pot2": "Jap*aSnxnte"}, {"word": "Jalp-aStanxn", "c_deletion": "JalaStanxn", "l_deletion": "JapaStanxn", "pot1": "Jal*aStanxn", "pot2": "Jap*aStanxn"}, {"word": "Jalp-aStvn", "c_deletion": "JalaStvn", "l_deletion": "JapaStvn", "pot1": "Jal*aStvn", "pot2": "Jap*aStvn"}, {"word": "Jalp-aSvyo", "c_deletion": "JalaSvyo", "l_deletion": "JapaSvyo", "pot1": "Jal*aSvyo", "pot2": "Jap*aSvyo"}, {"word": "Jalp-x", "c_deletion": "Jalx", "l_deletion": "Japx", "pot1": "Jal*x", "pot2": "Jap*x"}, {"word": "Jalp-xmyvn", "c_deletion": "Jalxmyvn", "l_deletion": "Japxmyvn", "pot1": "Jal*xmyvn", "pot2": "Jap*xmyvn"}, {"word": "Jalp-xniga", "c_deletion": "Jalxniga", "l_deletion": "Japxniga", "pot1": "Jal*xniga", "pot2": "Jap*xniga"}, {"word": "Jalp-xl", "c_deletion": "Jalxl", "l_deletion": "Japxl", "pot1": "Jal*xl", "pot2": "Jap*xl"}, {"word": "Jalp-xn", "c_deletion": "Jalxn", "l_deletion": "Japxn", "pot1": "Jal*xn", "pot2": "Jap*xn"}, {"word": "Jalp-xnte", "c_deletion": "Jalxnte", "l_deletion": "Japxnte", "pot1": "Jal*xnte", "pot2": "Jap*xnte"}, {"word": "Jalp-xnteto", "c_deletion": "Jalxnteto", "l_deletion": "Japxnteto", "pot1": "Jal*xnteto", "pot2": "Jap*xnteto"}, {"word": "Poknvlp-xn", "c_deletion": "Poknvlxn", "l_deletion": "Poknvpxn", "pot1": "Poknvl*xn", "pot2": "Poknvp*xn"}, {"word": "cilm-vcikeSta", "c_deletion": "cilvcikeSta", "l_deletion": "cimvcikeSta", "pot1": "cil*vcikeSta", "pot2": "cim*vcikeSta"}, {"word": "cilm-vciko", "c_deletion": "cilvciko", "l_deletion": "cimvciko", "pot1": "cil*vciko", "pot2": "cim*vciko"}, {"word": "cilm-vcilyvko", "c_deletion": "cilvcilyvko", "l_deletion": "cimvcilyvko", "pot1": "cil*vcilyvko", "pot2": "cim*vcilyvko"}, {"word": "cilm-vcinxn", "c_deletion": "cilvcinxn", "l_deletion": "cimvcinxn", "pot1": "cil*vcinxn", "pot2": "cim*vcinxn"}, {"word": "cilm-vcil", "c_deletion": "cilvcil", "l_deletion": "cimvcil", "pot1": "cil*vcil", "pot2": "cim*vcil"}, {"word": "cilm-vcilga", "c_deletion": "cilvcilga", "l_deletion": "cimvcilga", "pot1": "cil*vcilga", "pot2": "cim*vcilga"}, {"word": "cilm-vcyvto", "c_deletion": "cilvcyvto", "l_deletion": "cimvcyvto", "pot1": "cil*vcyvto", "pot2": "cim*vcyvto"}, {"word": "cilm-vcyvya", "c_deletion": "cilvcyvya", "l_deletion": "cimvcyvya", "pot1": "cil*vcyvya", "pot2": "cim*vcyvya"}, {"word": "cispalp-apvlin", "c_deletion": "cispalapvlin", "l_deletion": "cispapapvlin", "pot1": "cispal*apvlin", "pot2": "cispap*apvlin"}, {"word": "cispalp-aStvn", "c_deletion": "cispalaStvn", "l_deletion": "cispapaStvn", "pot1": "cispal*aStvn", "pot2": "cispap*aStvn"}, {"word": "cvlm-v", "c_deletion": "cvlv", "l_deletion": "cvmv", "pot1": "cvl*v", "pot2": "cvm*v"}, {"word": "cvlm-vciko", "c_deletion": "cvlvciko", "l_deletion": "cvmvciko", "pot1": "cvl*vciko", "pot2": "cvm*vciko"}, {"word": "cvlm-vciniga", "c_deletion": "cvlvciniga", "l_deletion": "cvmvciniga", "pot1": "cvl*vciniga", "pot2": "cvm*vciniga"}, {"word": "cvlm-vcinxn", "c_deletion": "cvlvcinxn", "l_deletion": "cvmvcinxn", "pot1": "cvl*vcinxn", "pot2": "cvm*vcinxn"}, {"word": "cvlm-vcin", "c_deletion": "cvlvcin", "l_deletion": "cvmvcin", "pot1": "cvl*vcin", "pot2": "cvm*vcin"}, {"word": "cvlm-vkaciko", "c_deletion": "cvlvkaciko", "l_deletion": "cvmvkaciko", "pot1": "cvl*vkaciko", "pot2": "cvm*vkaciko"}, {"word": "cvlm-vsv", "c_deletion": "cvlvsv", "l_deletion": "cvmvsv", "pot1": "cvl*vsv", "pot2": "cvm*vsv"}, {"word": "cvlm-vsvnxn", "c_deletion": "cvlvsvnxn", "l_deletion": "cvmvsvnxn", "pot1": "cvl*vsvnxn", "pot2": "cvm*vsvnxn"}, {"word": "cvlm-vsvpuTv", "c_deletion": "cvlvsvpuTv", "l_deletion": "cvmvsvpuTv", "pot1": "cvl*vsvpuTv", "pot2": "cvm*vsvpuTv"}, {"word": "cvlm-vsvto", "c_deletion": "cvlvsvto", "l_deletion": "cvmvsvto", "pot1": "cvl*vsvto", "pot2": "cvm*vsvto"}, {"word": "cvlm-vyo", "c_deletion": "cvlvyo", "l_deletion": "cvmvyo", "pot1": "cvl*vyo", "pot2": "cvm*vyo"}, {"word": "cvlm-vS", "c_deletion": "cvlvS", "l_deletion": "cvmvS", "pot1": "cvl*vS", "pot2": "cvm*vS"}, {"word": "cvlm-vScanhayo", "c_deletion": "cvlvScanhayo", "l_deletion": "cvmvScanhayo", "pot1": "cvl*vScanhayo", "pot2": "cvm*vScanhayo"}, {"word": "cvlm-vSkeScyo", "c_deletion": "cvlvSkeScyo", "l_deletion": "cvmvSkeScyo", "pot1": "cvl*vSkeScyo", "pot2": "cvm*vSkeScyo"}, {"word": "cvlm-vSvStvn", "c_deletion": "cvlvSvStvn", "l_deletion": "cvmvSvStvn", "pot1": "cvl*vSvStvn", "pot2": "cvm*vSvStvn"}, {"word": "cvlm-vSxmyvn", "c_deletion": "cvlvSxmyvn", "l_deletion": "cvmvSxmyvn", "pot1": "cvl*vSxmyvn", "pot2": "cvm*vSxmyvn"}, {"word": "cvlm-vSxmyvnxn", "c_deletion": "cvlvSxmyvnxn", "l_deletion": "cvmvSxmyvnxn", "pot1": "cvl*vSxmyvnxn", "pot2": "cvm*vSxmyvnxn"}, {"word": "cvlm-vSxniga", "c_deletion": "cvlvSxniga", "l_deletion": "cvmvSxniga", "pot1": "cvl*vSxniga", "pot2": "cvm*vSxniga"}, {"word": "cvlm-vSxl", "c_deletion": "cvlvSxl", "l_deletion": "cvmvSxl", "pot1": "cvl*vSxl", "pot2": "cvm*vSxl"}, {"word": "cvlm-x", "c_deletion": "cvlx", "l_deletion": "cvmx", "pot1": "cvl*x", "pot2": "cvm*x"}, {"word": "cvlm-xna", "c_deletion": "cvlxna", "l_deletion": "cvmxna", "pot1": "cvl*xna", "pot2": "cvm*xna"}, {"word": "cvlm-xniga", "c_deletion": "cvlxniga", "l_deletion": "cvmxniga", "pot1": "cvl*xniga", "pot2": "cvm*xniga"}, {"word": "cvlm-xnigan", "c_deletion": "cvlxnigan", "l_deletion": "cvmxnigan", "pot1": "cvl*xnigan", "pot2": "cvm*xnigan"}, {"word": "cvlm-xsicanhayo", "c_deletion": "cvlxsicanhayo", "l_deletion": "cvmxsicanhayo", "pot1": "cvl*xsicanhayo", "pot2": "cvm*xsicanhayo"}, {"word": "cvlm-xsikinxn", "c_deletion": "cvlxsikinxn", "l_deletion": "cvmxsikinxn", "pot1": "cvl*xsikinxn", "pot2": "cvm*xsikinxn"}, {"word": "cvlm-xsiniga", "c_deletion": "cvlxsiniga", "l_deletion": "cvmxsiniga", "pot1": "cvl*xsiniga", "pot2": "cvm*xsiniga"}, {"word": "cvlm-xsita", "c_deletion": "cvlxsita", "l_deletion": "cvmxsita", "pot1": "cvl*xsita", "pot2": "cvm*xsita"}, {"word": "cvlm-xsil", "c_deletion": "cvlxsil", "l_deletion": "cvmxsil", "pot1": "cvl*xsil", "pot2": "cvm*xsil"}, {"word": "cvlm-xsin", "c_deletion": "cvlxsin", "l_deletion": "cvmxsin", "pot1": "cvl*xsin", "pot2": "cvm*xsin"}, {"word": "cvlm-xsinte", "c_deletion": "cvlxsinte", "l_deletion": "cvmxsinte", "pot1": "cvl*xsinte", "pot2": "cvm*xsinte"}, {"word": "cvlm-xsyvkaciko", "c_deletion": "cvlxsyvkaciko", "l_deletion": "cvmxsyvkaciko", "pot1": "cvl*xsyvkaciko", "pot2": "cvm*xsyvkaciko"}, {"word": "cvlm-xsyvkacko", "c_deletion": "cvlxsyvkacko", "l_deletion": "cvmxsyvkacko", "pot1": "cvl*xsyvkacko", "pot2": "cvm*xsyvkacko"}, {"word": "cvlm-xsyvsv", "c_deletion": "cvlxsyvsv", "l_deletion": "cvmxsyvsv", "pot1": "cvl*xsyvsv", "pot2": "cvm*xsyvsv"}, {"word": "cvlm-xsyvSkvtxnyo", "c_deletion": "cvlxsyvSkvtxnyo", "l_deletion": "cvmxsyvSkvtxnyo", "pot1": "cvl*xsyvSkvtxnyo", "pot2": "cvm*xsyvSkvtxnyo"}, {"word": "cvlm-xsyvSxl", "c_deletion": "cvlxsyvSxl", "l_deletion": "cvmxsyvSxl", "pot1": "cvl*xsyvSxl", "pot2": "cvm*xsyvSxl"}, {"word": "cvlm-xl", "c_deletion": "cvlxl", "l_deletion": "cvmxl", "pot1": "cvl*xl", "pot2": "cvm*xl"}, {"word": "cvlm-xm", "c_deletion": "cvlxm", "l_deletion": "cvmxm", "pot1": "cvl*xm", "pot2": "cvm*xm"}, {"word": "cvlm-xmxl", "c_deletion": "cvlxmxl", "l_deletion": "cvmxmxl", "pot1": "cvl*xmxl", "pot2": "cvm*xmxl"}, {"word": "cvlm-xn", "c_deletion": "cvlxn", "l_deletion": "cvmxn", "pot1": "cvl*xn", "pot2": "cvm*xn"}, {"word": "cvlm-xnCxNina", "c_deletion": "cvlxnCxNina", "l_deletion": "cvmxnCxNina", "pot1": "cvl*xnCxNina", "pot2": "cvm*xnCxNina"}, {"word": "cvlm-xnCxNxlo", "c_deletion": "cvlxnCxNxlo", "l_deletion": "cvmxnCxNxlo", "pot1": "cvl*xnCxNxlo", "pot2": "cvm*xnCxNxlo"}, {"word": "cvlm-xnCxNxy", "c_deletion": "cvlxnCxNxy", "l_deletion": "cvmxnCxNxy", "pot1": "cvl*xnCxNxy", "pot2": "cvm*xnCxNxy"}, {"word": "cvlm-xni", "c_deletion": "cvlxni", "l_deletion": "cvmxni", "pot1": "cvl*xni", "pot2": "cvm*xni"}, {"word": "cvlm-xnika", "c_deletion": "cvlxnika", "l_deletion": "cvmxnika", "pot1": "cvl*xnika", "pot2": "cvm*xnika"}, {"word": "cvlm-xnilamyvn", "c_deletion": "cvlxnilamyvn", "l_deletion": "cvmxnilamyvn", "pot1": "cvl*xnilamyvn", "pot2": "cvm*xnilamyvn"}, {"word": "cvlm-xnilanxn", "c_deletion": "cvlxnilanxn", "l_deletion": "cvmxnilanxn", "pot1": "cvl*xnilanxn", "pot2": "cvm*xnilanxn"}, {"word": "cvlm-xniman", "c_deletion": "cvlxniman", "l_deletion": "cvmxniman", "pot1": "cvl*xniman", "pot2": "cvm*xniman"}, {"word": "cvlm-xniniga", "c_deletion": "cvlxniniga", "l_deletion": "cvmxniniga", "pot1": "cvl*xniniga", "pot2": "cvm*xniniga"}, {"word": "cvlm-xnita", "c_deletion": "cvlxnita", "l_deletion": "cvmxnita", "pot1": "cvl*xnita", "pot2": "cvm*xnita"}, {"word": "cvlm-xnitxl", "c_deletion": "cvlxnitxl", "l_deletion": "cvmxnitxl", "pot1": "cvl*xnitxl", "pot2": "cvm*xnitxl"}, {"word": "cvlm-xnitxle", "c_deletion": "cvlxnitxle", "l_deletion": "cvmxnitxle", "pot1": "cvl*xnitxle", "pot2": "cvm*xnitxle"}, {"word": "cvlm-xnitxleke", "c_deletion": "cvlxnitxleke", "l_deletion": "cvmxnitxleke", "pot1": "cvl*xnitxleke", "pot2": "cvm*xnitxleke"}, {"word": "cvlm-xnitxleketo", "c_deletion": "cvlxnitxleketo", "l_deletion": "cvmxnitxleketo", "pot1": "cvl*xnitxleketo", "pot2": "cvm*xnitxleketo"}, {"word": "cvlm-xnitxlhanTe", "c_deletion": "cvlxnitxlhanTe", "l_deletion": "cvmxnitxlhanTe", "pot1": "cvl*xnitxlhanTe", "pot2": "cvm*xnitxlhanTe"}, {"word": "cvlm-xnitxlhanTeto", "c_deletion": "cvlxnitxlhanTeto", "l_deletion": "cvmxnitxlhanTeto", "pot1": "cvl*xnitxlhanTeto", "pot2": "cvm*xnitxlhanTeto"}, {"word": "cvlm-xnitxli", "c_deletion": "cvlxnitxli", "l_deletion": "cvmxnitxli", "pot1": "cvl*xnitxli", "pot2": "cvm*xnitxli"}, {"word": "cvlm-xnitxlina", "c_deletion": "cvlxnitxlina", "l_deletion": "cvmxnitxlina", "pot1": "cvl*xnitxlina", "pot2": "cvm*xnitxlina"}, {"word": "cvlm-xnitxlivSxmyvn", "c_deletion": "cvlxnitxlivSxmyvn", "l_deletion": "cvmxnitxlivSxmyvn", "pot1": "cvl*xnitxlivSxmyvn", "pot2": "cvm*xnitxlivSxmyvn"}, {"word": "cvlm-xnitxltapci", "c_deletion": "cvlxnitxltapci", "l_deletion": "cvmxnitxltapci", "pot1": "cvl*xnitxltapci", "pot2": "cvm*xnitxltapci"}, {"word": "cvlm-xnitxlto", "c_deletion": "cvlxnitxlto", "l_deletion": "cvmxnitxlto", "pot1": "cvl*xnitxlto", "pot2": "cvm*xnitxlto"}, {"word": "cvlm-xnitxlxl", "c_deletion": "cvlxnitxlxl", "l_deletion": "cvmxnitxlxl", "pot1": "cvl*xnitxlxl", "pot2": "cvm*xnitxlxl"}, {"word": "cvlm-xnitxlxn", "c_deletion": "cvlxnitxlxn", "l_deletion": "cvmxnitxlxn", "pot1": "cvl*xnitxlxn", "pot2": "cvm*xnitxlxn"}, {"word": "cvlm-xnitxlxy", "c_deletion": "cvlxnitxlxy", "l_deletion": "cvmxnitxlxy", "pot1": "cvl*xnitxlxy", "pot2": "cvm*xnitxlxy"}, {"word": "cvlm-xnixy", "c_deletion": "cvlxnixy", "l_deletion": "cvmxnixy", "pot1": "cvl*xnixy", "pot2": "cvm*xnixy"}, {"word": "cvlm-xnte", "c_deletion": "cvlxnte", "l_deletion": "cvmxnte", "pot1": "cvl*xnte", "pot2": "cvm*xnte"}, {"word": "halT-acuko", "c_deletion": "halacuko", "l_deletion": "haTacuko", "pot1": "hal*acuko", "pot2": "haT*acuko"}, {"word": "halT-acukvna", "c_deletion": "halacukvna", "l_deletion": "haTacukvna", "pot1": "hal*acukvna", "pot2": "haT*acukvna"}, {"word": "halT-acutvlako", "c_deletion": "halacutvlako", "l_deletion": "haTacutvlako", "pot1": "hal*acutvlako", "pot2": "haT*acutvlako"}, {"word": "halT-acuntatxnka", "c_deletion": "halacuntatxnka", "l_deletion": "haTacuntatxnka", "pot1": "hal*acuntatxnka", "pot2": "haT*acuntatxnka"}, {"word": "halT-akamyvnsv", "c_deletion": "halakamyvnsv", "l_deletion": "haTakamyvnsv", "pot1": "hal*akamyvnsv", "pot2": "haT*akamyvnsv"}, {"word": "halT-asv", "c_deletion": "halasv", "l_deletion": "haTasv", "pot1": "hal*asv", "pot2": "haT*asv"}, {"word": "halT-ayo", "c_deletion": "halayo", "l_deletion": "haTayo", "pot1": "hal*ayo", "pot2": "haT*ayo"}, {"word": "halT-aSxl", "c_deletion": "halaSxl", "l_deletion": "haTaSxl", "pot1": "hal*aSxl", "pot2": "haT*aSxl"}, {"word": "halT-xmyvn", "c_deletion": "halxmyvn", "l_deletion": "haTxmyvn", "pot1": "hal*xmyvn", "pot2": "haT*xmyvn"}, {"word": "hemalk-xm", "c_deletion": "hemalxm", "l_deletion": "hemakxm", "pot1": "hemal*xm", "pot2": "hemak*xm"}, {"word": "hulT-v", "c_deletion": "hulv", "l_deletion": "huTv", "pot1": "hul*v", "pot2": "huT*v"}, {"word": "hulT-vpoko", "c_deletion": "hulvpoko", "l_deletion": "huTvpoko", "pot1": "hul*vpoko", "pot2": "huT*vpoko"}, {"word": "hulT-vpomyvn", "c_deletion": "hulvpomyvn", "l_deletion": "huTvpomyvn", "pot1": "hul*vpomyvn", "pot2": "huT*vpomyvn"}, {"word": "hulT-vpomyvnsv", "c_deletion": "hulvpomyvnsv", "l_deletion": "huTvpomyvnsv", "pot1": "hul*vpomyvnsv", "pot2": "huT*vpomyvnsv"}, {"word": "hulT-vposin", "c_deletion": "hulvposin", "l_deletion": "huTvposin", "pot1": "hul*vposin", "pot2": "huT*vposin"}, {"word": "hulT-vpotaka", "c_deletion": "hulvpotaka", "l_deletion": "huTvpotaka", "pot1": "hul*vpotaka", "pot2": "huT*vpotaka"}, {"word": "hulT-vpotvni", "c_deletion": "hulvpotvni", "l_deletion": "huTvpotvni", "pot1": "hul*vpotvni", "pot2": "huT*vpotvni"}, {"word": "hulT-vpwaya", "c_deletion": "hulvpwaya", "l_deletion": "huTvpwaya", "pot1": "hul*vpwaya", "pot2": "huT*vpwaya"}, {"word": "ilk-v", "c_deletion": "ilv", "l_deletion": "ikv", "pot1": "il*v", "pot2": "ik*v"}, {"word": "ilk-vcin", "c_deletion": "ilvcin", "l_deletion": "ikvcin", "pot1": "il*vcin", "pot2": "ik*vcin"}, {"word": "ilk-vcuca", "c_deletion": "ilvcuca", "l_deletion": "ikvcuca", "pot1": "il*vcuca", "pot2": "ik*vcuca"}, {"word": "ilk-vcuke", "c_deletion": "ilvcuke", "l_deletion": "ikvcuke", "pot1": "il*vcuke", "pot2": "ik*vcuke"}, {"word": "ilk-vcukin", "c_deletion": "ilvcukin", "l_deletion": "ikvcukin", "pot1": "il*vcukin", "pot2": "ik*vcukin"}, {"word": "ilk-vcuko", "c_deletion": "ilvcuko", "l_deletion": "ikvcuko", "pot1": "il*vcuko", "pot2": "ik*vcuko"}, {"word": "ilk-vcukvna", "c_deletion": "ilvcukvna", "l_deletion": "ikvcukvna", "pot1": "il*vcukvna", "pot2": "ik*vcukvna"}, {"word": "ilk-vcumyvn", "c_deletion": "ilvcumyvn", "l_deletion": "ikvcumyvn", "pot1": "il*vcumyvn", "pot2": "ik*vcumyvn"}, {"word": "ilk-vcumyvnsv", "c_deletion": "ilvcumyvnsv", "l_deletion": "ikvcumyvnsv", "pot1": "il*vcumyvnsv", "pot2": "ik*vcumyvnsv"}, {"word": "ilk-vcunxn", "c_deletion": "ilvcunxn", "l_deletion": "ikvcunxn", "pot1": "il*vcunxn", "pot2": "ik*vcunxn"}, {"word": "ilk-vcunxnte", "c_deletion": "ilvcunxnte", "l_deletion": "ikvcunxnte", "pot1": "il*vcunxnte", "pot2": "ik*vcunxnte"}, {"word": "ilk-vcusikito", "c_deletion": "ilvcusikito", "l_deletion": "ikvcusikito", "pot1": "il*vcusikito", "pot2": "ik*vcusikito"}, {"word": "ilk-vcusikvtxn", "c_deletion": "ilvcusikvtxn", "l_deletion": "ikvcusikvtxn", "pot1": "il*vcusikvtxn", "pot2": "ik*vcusikvtxn"}, {"word": "ilk-vcun", "c_deletion": "ilvcun", "l_deletion": "ikvcun", "pot1": "il*vcun", "pot2": "ik*vcun"}, {"word": "ilk-vcwvSkvtxn", "c_deletion": "ilvcwvSkvtxn", "l_deletion": "ikvcwvSkvtxn", "pot1": "il*vcwvSkvtxn", "pot2": "ik*vcwvSkvtxn"}, {"word": "ilk-vcyvsv", "c_deletion": "ilvcyvsv", "l_deletion": "ikvcyvsv", "pot1": "il*vcyvsv", "pot2": "ik*vcyvsv"}, {"word": "ilk-vkanxn", "c_deletion": "ilvkanxn", "l_deletion": "ikvkanxn", "pot1": "il*vkanxn", "pot2": "ik*vkanxn"}, {"word": "ilk-vla", "c_deletion": "ilvla", "l_deletion": "ikvla", "pot1": "il*vla", "pot2": "ik*vla"}, {"word": "ilk-vneko", "c_deletion": "ilvneko", "l_deletion": "ikvneko", "pot1": "il*vneko", "pot2": "ik*vneko"}, {"word": "ilk-vnenxn", "c_deletion": "ilvnenxn", "l_deletion": "ikvnenxn", "pot1": "il*vnenxn", "pot2": "ik*vnenxn"}, {"word": "ilk-vpoci", "c_deletion": "ilvpoci", "l_deletion": "ikvpoci", "pot1": "il*vpoci", "pot2": "ik*vpoci"}, {"word": "ilk-vpocinxn", "c_deletion": "ilvpocinxn", "l_deletion": "ikvpocinxn", "pot1": "il*vpocinxn", "pot2": "ik*vpocinxn"}, {"word": "ilk-vpocin", "c_deletion": "ilvpocin", "l_deletion": "ikvpocin", "pot1": "il*vpocin", "pot2": "ik*vpocin"}, {"word": "ilk-vpokie", "c_deletion": "ilvpokie", "l_deletion": "ikvpokie", "pot1": "il*vpokie", "pot2": "ik*vpokie"}, {"word": "ilk-vpokinxn", "c_deletion": "ilvpokinxn", "l_deletion": "ikvpokinxn", "pot1": "il*vpokinxn", "pot2": "ik*vpokinxn"}, {"word": "ilk-vpokin", "c_deletion": "ilvpokin", "l_deletion": "ikvpokin", "pot1": "il*vpokin", "pot2": "ik*vpokin"}, {"word": "ilk-vpoko", "c_deletion": "ilvpoko", "l_deletion": "ikvpoko", "pot1": "il*vpoko", "pot2": "ik*vpoko"}, {"word": "ilk-vpokonxn", "c_deletion": "ilvpokonxn", "l_deletion": "ikvpokonxn", "pot1": "il*vpokonxn", "pot2": "ik*vpokonxn"}, {"word": "ilk-vpolako", "c_deletion": "ilvpolako", "l_deletion": "ikvpolako", "pot1": "il*vpolako", "pot2": "ik*vpolako"}, {"word": "ilk-vpolv", "c_deletion": "ilvpolv", "l_deletion": "ikvpolv", "pot1": "il*vpolv", "pot2": "ik*vpolv"}, {"word": "ilk-vpomyvn", "c_deletion": "ilvpomyvn", "l_deletion": "ikvpomyvn", "pot1": "il*vpomyvn", "pot2": "ik*vpomyvn"}, {"word": "ilk-vpomyvnsv", "c_deletion": "ilvpomyvnsv", "l_deletion": "ikvpomyvnsv", "pot1": "il*vpomyvnsv", "pot2": "ik*vpomyvnsv"}, {"word": "ilk-vpomyvnxn", "c_deletion": "ilvpomyvnxn", "l_deletion": "ikvpomyvnxn", "pot1": "il*vpomyvnxn", "pot2": "ik*vpomyvnxn"}, {"word": "ilk-vponiga", "c_deletion": "ilvponiga", "l_deletion": "ikvponiga", "pot1": "il*vponiga", "pot2": "ik*vponiga"}, {"word": "ilk-vponxn", "c_deletion": "ilvponxn", "l_deletion": "ikvponxn", "pot1": "il*vponxn", "pot2": "ik*vponxn"}, {"word": "ilk-vposinxn", "c_deletion": "ilvposinxn", "l_deletion": "ikvposinxn", "pot1": "il*vposinxn", "pot2": "ik*vposinxn"}, {"word": "ilk-vposintako", "c_deletion": "ilvposintako", "l_deletion": "ikvposintako", "pot1": "il*vposintako", "pot2": "ik*vposintako"}, {"word": "ilk-vposyvScyo", "c_deletion": "ilvposyvScyo", "l_deletion": "ikvposyvScyo", "pot1": "il*vposyvScyo", "pot2": "ik*vposyvScyo"}, {"word": "ilk-vposyvSvyo", "c_deletion": "ilvposyvSvyo", "l_deletion": "ikvposyvSvyo", "pot1": "il*vposyvSvyo", "pot2": "ik*vposyvSvyo"}, {"word": "ilk-vposyvSxlgayo", "c_deletion": "ilvposyvSxlgayo", "l_deletion": "ikvposyvSxlgayo", "pot1": "il*vposyvSxlgayo", "pot2": "ik*vposyvSxlgayo"}, {"word": "ilk-vpol", "c_deletion": "ilvpol", "l_deletion": "ikvpol", "pot1": "il*vpol", "pot2": "ik*vpol"}, {"word": "ilk-vpon", "c_deletion": "ilvpon", "l_deletion": "ikvpon", "pot1": "il*vpon", "pot2": "ik*vpon"}, {"word": "ilk-vpwaculke", "c_deletion": "ilvpwaculke", "l_deletion": "ikvpwaculke", "pot1": "il*vpwaculke", "pot2": "ik*vpwaculke"}, {"word": "ilk-vpwato", "c_deletion": "ilvpwato", "l_deletion": "ikvpwato", "pot1": "il*vpwato", "pot2": "ik*vpwato"}, {"word": "ilk-vpwaSkoyo", "c_deletion": "ilvpwaSkoyo", "l_deletion": "ikvpwaSkoyo", "pot1": "il*vpwaSkoyo", "pot2": "ik*vpwaSkoyo"}, {"word": "ilk-vpwaSkvtxnyo", "c_deletion": "ilvpwaSkvtxnyo", "l_deletion": "ikvpwaSkvtxnyo", "pot1": "il*vpwaSkvtxnyo", "pot2": "ik*vpwaSkvtxnyo"}, {"word": "ilk-vpwaSnxnte", "c_deletion": "ilvpwaSnxnte", "l_deletion": "ikvpwaSnxnte", "pot1": "il*vpwaSnxnte", "pot2": "ik*vpwaSnxnte"}, {"word": "ilk-vpwaSnxnteyo", "c_deletion": "ilvpwaSnxnteyo", "l_deletion": "ikvpwaSnxnteyo", "pot1": "il*vpwaSnxnteyo", "pot2": "ik*vpwaSnxnteyo"}, {"word": "ilk-vpwaStan", "c_deletion": "ilvpwaStan", "l_deletion": "ikvpwaStan", "pot1": "il*vpwaStan", "pot2": "ik*vpwaStan"}, {"word": "ilk-vpwaStvn", "c_deletion": "ilvpwaStvn", "l_deletion": "ikvpwaStvn", "pot1": "il*vpwaStvn", "pot2": "ik*vpwaStvn"}, {"word": "ilk-vpwaSv", "c_deletion": "ilvpwaSv", "l_deletion": "ikvpwaSv", "pot1": "il*vpwaSv", "pot2": "ik*vpwaSv"}, {"word": "ilk-vpwaSvyo", "c_deletion": "ilvpwaSvyo", "l_deletion": "ikvpwaSvyo", "pot1": "il*vpwaSvyo", "pot2": "ik*vpwaSvyo"}, {"word": "ilk-vpwaSxl", "c_deletion": "ilvpwaSxl", "l_deletion": "ikvpwaSxl", "pot1": "il*vpwaSxl", "pot2": "ik*vpwaSxl"}, {"word": "ilk-vsv", "c_deletion": "ilvsv", "l_deletion": "ikvsv", "pot1": "il*vsv", "pot2": "ik*vsv"}, {"word": "ilk-vto", "c_deletion": "ilvto", "l_deletion": "ikvto", "pot1": "il*vto", "pot2": "ik*vto"}, {"word": "ilk-vtxlipni", "c_deletion": "ilvtxlipni", "l_deletion": "ikvtxlipni", "pot1": "il*vtxlipni", "pot2": "ik*vtxlipni"}, {"word": "ilk-vya", "c_deletion": "ilvya", "l_deletion": "ikvya", "pot1": "il*vya", "pot2": "ik*vya"}, {"word": "ilk-vyaci", "c_deletion": "ilvyaci", "l_deletion": "ikvyaci", "pot1": "il*vyaci", "pot2": "ik*vyaci"}, {"word": "ilk-vyacilako", "c_deletion": "ilvyacilako", "l_deletion": "ikvyacilako", "pot1": "il*vyacilako", "pot2": "ik*vyacilako"}, {"word": "ilk-vyakeSta", "c_deletion": "ilvyakeSta", "l_deletion": "ikvyakeSta", "pot1": "il*vyakeSta", "pot2": "ik*vyakeSta"}, {"word": "ilk-vyo", "c_deletion": "ilvyo", "l_deletion": "ikvyo", "pot1": "il*vyo", "pot2": "ik*vyo"}, {"word": "ilk-vScanha", "c_deletion": "ilvScanha", "l_deletion": "ikvScanha", "pot1": "il*vScanha", "pot2": "ik*vScanha"}, {"word": "ilk-vSki", "c_deletion": "ilvSki", "l_deletion": "ikvSki", "pot1": "il*vSki", "pot2": "ik*vSki"}, {"word": "ilk-vSko", "c_deletion": "ilvSko", "l_deletion": "ikvSko", "pot1": "il*vSko", "pot2": "ik*vSko"}, {"word": "ilk-vSkvtxn", "c_deletion": "ilvSkvtxn", "l_deletion": "ikvSkvtxn", "pot1": "il*vSkvtxn", "pot2": "ik*vSkvtxn"}, {"word": "ilk-vSkvtxnyo", "c_deletion": "ilvSkvtxnyo", "l_deletion": "ikvSkvtxnyo", "pot1": "il*vSkvtxnyo", "pot2": "ik*vSkvtxnyo"}, {"word": "ilk-vSnxnte", "c_deletion": "ilvSnxnte", "l_deletion": "ikvSnxnte", "pot1": "il*vSnxnte", "pot2": "ik*vSnxnte"}, {"word": "ilk-vSnxnteyo", "c_deletion": "ilvSnxnteyo", "l_deletion": "ikvSnxnteyo", "pot1": "il*vSnxnteyo", "pot2": "ik*vSnxnteyo"}, {"word": "ilk-vSta", "c_deletion": "ilvSta", "l_deletion": "ikvSta", "pot1": "il*vSta", "pot2": "ik*vSta"}, {"word": "ilk-vStako", "c_deletion": "ilvStako", "l_deletion": "ikvStako", "pot1": "il*vStako", "pot2": "ik*vStako"}, {"word": "ilk-vStvn", "c_deletion": "ilvStvn", "l_deletion": "ikvStvn", "pot1": "il*vStvn", "pot2": "ik*vStvn"}, {"word": "ilk-vSv", "c_deletion": "ilvSv", "l_deletion": "ikvSv", "pot1": "il*vSv", "pot2": "ik*vSv"}, {"word": "ilk-vSvyo", "c_deletion": "ilvSvyo", "l_deletion": "ikvSvyo", "pot1": "il*vSvyo", "pot2": "ik*vSvyo"}, {"word": "ilk-vSvSkvtxn", "c_deletion": "ilvSvSkvtxn", "l_deletion": "ikvSvSkvtxn", "pot1": "il*vSvSkvtxn", "pot2": "ik*vSvSkvtxn"}, {"word": "ilk-vSvSkvtxnyo", "c_deletion": "ilvSvSkvtxnyo", "l_deletion": "ikvSvSkvtxnyo", "pot1": "il*vSvSkvtxnyo", "pot2": "ik*vSvSkvtxnyo"}, {"word": "ilk-vSvSnxn", "c_deletion": "ilvSvSnxn", "l_deletion": "ikvSvSnxn", "pot1": "il*vSvSnxn", "pot2": "ik*vSvSnxn"}, {"word": "ilk-vSvSnxnte", "c_deletion": "ilvSvSnxnte", "l_deletion": "ikvSvSnxnte", "pot1": "il*vSvSnxnte", "pot2": "ik*vSvSnxnte"}, {"word": "ilk-vSvSnxnteyo", "c_deletion": "ilvSvSnxnteyo", "l_deletion": "ikvSvSnxnteyo", "pot1": "il*vSvSnxnteyo", "pot2": "ik*vSvSnxnteyo"}, {"word": "ilk-vSvSsxpnita", "c_deletion": "ilvSvSsxpnita", "l_deletion": "ikvSvSsxpnita", "pot1": "il*vSvSsxpnita", "pot2": "ik*vSvSsxpnita"}, {"word": "ilk-vSx", "c_deletion": "ilvSx", "l_deletion": "ikvSx", "pot1": "il*vSx", "pot2": "ik*vSx"}, {"word": "ilk-vSxl", "c_deletion": "ilvSxl", "l_deletion": "ikvSxl", "pot1": "il*vSxl", "pot2": "ik*vSxl"}, {"word": "ilk-xla", "c_deletion": "ilxla", "l_deletion": "ikxla", "pot1": "il*xla", "pot2": "ik*xla"}, {"word": "ilk-xlyvko", "c_deletion": "ilxlyvko", "l_deletion": "ikxlyvko", "pot1": "il*xlyvko", "pot2": "ik*xlyvko"}, {"word": "ilk-xmyvn", "c_deletion": "ilxmyvn", "l_deletion": "ikxmyvn", "pot1": "il*xmyvn", "pot2": "ik*xmyvn"}, {"word": "ilk-xmyvnsv", "c_deletion": "ilxmyvnsv", "l_deletion": "ikxmyvnsv", "pot1": "il*xmyvnsv", "pot2": "ik*xmyvnsv"}, {"word": "ilk-xmyvnsvto", "c_deletion": "ilxmyvnsvto", "l_deletion": "ikxmyvnsvto", "pot1": "il*xmyvnsvto", "pot2": "ik*xmyvnsvto"}, {"word": "ilk-xmyvnxn", "c_deletion": "ilxmyvnxn", "l_deletion": "ikxmyvnxn", "pot1": "il*xmyvnxn", "pot2": "ik*xmyvnxn"}, {"word": "ilk-xniga", "c_deletion": "ilxniga", "l_deletion": "ikxniga", "pot1": "il*xniga", "pot2": "ik*xniga"}, {"word": "ilk-xseyo", "c_deletion": "ilxseyo", "l_deletion": "ikxseyo", "pot1": "il*xseyo", "pot2": "ik*xseyo"}, {"word": "ilk-xsinxn", "c_deletion": "ilxsinxn", "l_deletion": "ikxsinxn", "pot1": "il*xsinxn", "pot2": "ik*xsinxn"}, {"word": "ilk-xsinxnci", "c_deletion": "ilxsinxnci", "l_deletion": "ikxsinxnci", "pot1": "il*xsinxnci", "pot2": "ik*xsinxnci"}, {"word": "ilk-xsyvsv", "c_deletion": "ilxsyvsv", "l_deletion": "ikxsyvsv", "pot1": "il*xsyvsv", "pot2": "ik*xsyvsv"}, {"word": "ilk-xsyvSkeSvyo", "c_deletion": "ilxsyvSkeSvyo", "l_deletion": "ikxsyvSkeSvyo", "pot1": "il*xsyvSkeSvyo", "pot2": "ik*xsyvSkeSvyo"}, {"word": "ilk-xl", "c_deletion": "ilxl", "l_deletion": "ikxl", "pot1": "il*xl", "pot2": "ik*xl"}, {"word": "ilk-xn", "c_deletion": "ilxn", "l_deletion": "ikxn", "pot1": "il*xn", "pot2": "ik*xn"}, {"word": "kalk-a", "c_deletion": "kala", "l_deletion": "kaka", "pot1": "kal*a", "pot2": "kak*a"}, {"word": "kalk-amvkko", "c_deletion": "kalamvkko", "l_deletion": "kakamvkko", "pot1": "kal*amvkko", "pot2": "kak*amvkko"}, {"word": "kalk-amvknxn", "c_deletion": "kalamvknxn", "l_deletion": "kakamvknxn", "pot1": "kal*amvknxn", "pot2": "kak*amvknxn"}, {"word": "kalk-amvkxn", "c_deletion": "kalamvkxn", "l_deletion": "kakamvkxn", "pot1": "kal*amvkxn", "pot2": "kak*amvkxn"}, {"word": "kolm-a", "c_deletion": "kola", "l_deletion": "koma", "pot1": "kol*a", "pot2": "kom*a"}, {"word": "kolm-xl", "c_deletion": "kolxl", "l_deletion": "komxl", "pot1": "kol*xl", "pot2": "kom*xl"}, {"word": "kulk-vciko", "c_deletion": "kulvciko", "l_deletion": "kukvciko", "pot1": "kul*vciko", "pot2": "kuk*vciko"}, {"word": "kulk-vSko", "c_deletion": "kulvSko", "l_deletion": "kukvSko", "pot1": "kul*vSko", "pot2": "kuk*vSko"}, {"word": "kulk-vSvyo", "c_deletion": "kulvSvyo", "l_deletion": "kukvSvyo", "pot1": "kul*vSvyo", "pot2": "kuk*vSvyo"}, {"word": "kulk-xn", "c_deletion": "kulxn", "l_deletion": "kukxn", "pot1": "kul*xn", "pot2": "kuk*xn"}, {"word": "kulm-v", "c_deletion": "kulv", "l_deletion": "kumv", "pot1": "kul*v", "pot2": "kum*v"}, {"word": "kulm-vkamyvnsv", "c_deletion": "kulvkamyvnsv", "l_deletion": "kumvkamyvnsv", "pot1": "kul*vkamyvnsv", "pot2": "kum*vkamyvnsv"}, {"word": "kulm-vsv", "c_deletion": "kulvsv", "l_deletion": "kumvsv", "pot1": "kul*vsv", "pot2": "kum*vsv"}, {"word": "kulm-vto", "c_deletion": "kulvto", "l_deletion": "kumvto", "pot1": "kul*vto", "pot2": "kum*vto"}, {"word": "kulm-vya", "c_deletion": "kulvya", "l_deletion": "kumvya", "pot1": "kul*vya", "pot2": "kum*vya"}, {"word": "kulm-vSci", "c_deletion": "kulvSci", "l_deletion": "kumvSci", "pot1": "kul*vSci", "pot2": "kum*vSci"}, {"word": "kulm-vSvyo", "c_deletion": "kulvSvyo", "l_deletion": "kumvSvyo", "pot1": "kul*vSvyo", "pot2": "kum*vSvyo"}, {"word": "kulm-vSxmyvn", "c_deletion": "kulvSxmyvn", "l_deletion": "kumvSxmyvn", "pot1": "kul*vSxmyvn", "pot2": "kum*vSxmyvn"}, {"word": "kulm-xmyvn", "c_deletion": "kulxmyvn", "l_deletion": "kumxmyvn", "pot1": "kul*xmyvn", "pot2": "kum*xmyvn"}, {"word": "kulm-xmyvnsv", "c_deletion": "kulxmyvnsv", "l_deletion": "kumxmyvnsv", "pot1": "kul*xmyvnsv", "pot2": "kum*xmyvnsv"}, {"word": "kulm-xmyvnxn", "c_deletion": "kulxmyvnxn", "l_deletion": "kumxmyvnxn", "pot1": "kul*xmyvnxn", "pot2": "kum*xmyvnxn"}, {"word": "kulm-xl", "c_deletion": "kulxl", "l_deletion": "kumxl", "pot1": "kul*xl", "pot2": "kum*xl"}, {"word": "kxlk-v", "c_deletion": "kxlv", "l_deletion": "kxkv", "pot1": "kxl*v", "pot2": "kxk*v"}, {"word": "kxlk-vcwvScyo", "c_deletion": "kxlvcwvScyo", "l_deletion": "kxkvcwvScyo", "pot1": "kxl*vcwvScyo", "pot2": "kxk*vcwvScyo"}, {"word": "kxlk-vcwvSnxnte", "c_deletion": "kxlvcwvSnxnte", "l_deletion": "kxkvcwvSnxnte", "pot1": "kxl*vcwvSnxnte", "pot2": "kxk*vcwvSnxnte"}, {"word": "kxlk-vmvkko", "c_deletion": "kxlvmvkko", "l_deletion": "kxkvmvkko", "pot1": "kxl*vmvkko", "pot2": "kxk*vmvkko"}, {"word": "kxlk-vmvktvniman", "c_deletion": "kxlvmvktvniman", "l_deletion": "kxkvmvktvniman", "pot1": "kxl*vmvktvniman", "pot2": "kxk*vmvktvniman"}, {"word": "kxlk-vsv", "c_deletion": "kxlvsv", "l_deletion": "kxkvsv", "pot1": "kxl*vsv", "pot2": "kxk*vsv"}, {"word": "kxlk-vto", "c_deletion": "kxlvto", "l_deletion": "kxkvto", "pot1": "kxl*vto", "pot2": "kxk*vto"}, {"word": "kxlk-vyo", "c_deletion": "kxlvyo", "l_deletion": "kxkvyo", "pot1": "kxl*vyo", "pot2": "kxk*vyo"}, {"word": "kxlk-vStanxn", "c_deletion": "kxlvStanxn", "l_deletion": "kxkvStanxn", "pot1": "kxl*vStanxn", "pot2": "kxk*vStanxn"}, {"word": "kxlk-vStvn", "c_deletion": "kxlvStvn", "l_deletion": "kxkvStvn", "pot1": "kxl*vStvn", "pot2": "kxk*vStvn"}, {"word": "kxlk-xlyvko", "c_deletion": "kxlxlyvko", "l_deletion": "kxkxlyvko", "pot1": "kxl*xlyvko", "pot2": "kxk*xlyvko"}, {"word": "kxlk-xmyvn", "c_deletion": "kxlxmyvn", "l_deletion": "kxkxmyvn", "pot1": "kxl*xmyvn", "pot2": "kxk*xmyvn"}, {"word": "kxlk-xmyvnsv", "c_deletion": "kxlxmyvnsv", "l_deletion": "kxkxmyvnsv", "pot1": "kxl*xmyvnsv", "pot2": "kxk*xmyvnsv"}, {"word": "kxlk-xl", "c_deletion": "kxlxl", "l_deletion": "kxkxl", "pot1": "kxl*xl", "pot2": "kxk*xl"}, {"word": "kxlk-xn", "c_deletion": "kxlxn", "l_deletion": "kxkxn", "pot1": "kxl*xn", "pot2": "kxk*xn"}, {"word": "malk-a", "c_deletion": "mala", "l_deletion": "maka", "pot1": "mal*a", "pot2": "mak*a"}, {"word": "malk-acike", "c_deletion": "malacike", "l_deletion": "makacike", "pot1": "mal*acike", "pot2": "mak*acike"}, {"word": "malk-aciko", "c_deletion": "malaciko", "l_deletion": "makaciko", "pot1": "mal*aciko", "pot2": "mak*aciko"}, {"word": "malk-acinxn", "c_deletion": "malacinxn", "l_deletion": "makacinxn", "pot1": "mal*acinxn", "pot2": "mak*acinxn"}, {"word": "malk-acin", "c_deletion": "malacin", "l_deletion": "makacin", "pot1": "mal*acin", "pot2": "mak*acin"}, {"word": "malk-acintako", "c_deletion": "malacintako", "l_deletion": "makacintako", "pot1": "mal*acintako", "pot2": "mak*acintako"}, {"word": "malk-acyvyo", "c_deletion": "malacyvyo", "l_deletion": "makacyvyo", "pot1": "mal*acyvyo", "pot2": "mak*acyvyo"}, {"word": "malk-asv", "c_deletion": "malasv", "l_deletion": "makasv", "pot1": "mal*asv", "pot2": "mak*asv"}, {"word": "malk-ato", "c_deletion": "malato", "l_deletion": "makato", "pot1": "mal*ato", "pot2": "mak*ato"}, {"word": "malk-ayo", "c_deletion": "malayo", "l_deletion": "makayo", "pot1": "mal*ayo", "pot2": "mak*ayo"}, {"word": "malk-aStaka", "c_deletion": "malaStaka", "l_deletion": "makaStaka", "pot1": "mal*aStaka", "pot2": "mak*aStaka"}, {"word": "malk-aStvn", "c_deletion": "malaStvn", "l_deletion": "makaStvn", "pot1": "mal*aStvn", "pot2": "mak*aStvn"}, {"word": "malk-aSvSkvtxnyo", "c_deletion": "malaSvSkvtxnyo", "l_deletion": "makaSvSkvtxnyo", "pot1": "mal*aSvSkvtxnyo", "pot2": "mak*aSvSkvtxnyo"}, {"word": "malk-aSxmyvn", "c_deletion": "malaSxmyvn", "l_deletion": "makaSxmyvn", "pot1": "mal*aSxmyvn", "pot2": "mak*aSxmyvn"}, {"word": "malk-xmyvn", "c_deletion": "malxmyvn", "l_deletion": "makxmyvn", "pot1": "mal*xmyvn", "pot2": "mak*xmyvn"}, {"word": "malk-xmyvnsv", "c_deletion": "malxmyvnsv", "l_deletion": "makxmyvnsv", "pot1": "mal*xmyvnsv", "pot2": "mak*xmyvnsv"}, {"word": "malk-xl", "c_deletion": "malxl", "l_deletion": "makxl", "pot1": "mal*xl", "pot2": "mak*xl"}, {"word": "malk-xn", "c_deletion": "malxn", "l_deletion": "makxn", "pot1": "mal*xn", "pot2": "mak*xn"}, {"word": "nalk-a", "c_deletion": "nala", "l_deletion": "naka", "pot1": "nal*a", "pot2": "nak*a"}, {"word": "nalk-acyvSxl", "c_deletion": "nalacyvSxl", "l_deletion": "nakacyvSxl", "pot1": "nal*acyvSxl", "pot2": "nak*acyvSxl"}, {"word": "nalk-asv", "c_deletion": "nalasv", "l_deletion": "nakasv", "pot1": "nal*asv", "pot2": "nak*asv"}, {"word": "nalk-aSko", "c_deletion": "nalaSko", "l_deletion": "nakaSko", "pot1": "nal*aSko", "pot2": "nak*aSko"}, {"word": "nalk-xn", "c_deletion": "nalxn", "l_deletion": "nakxn", "pot1": "nal*xn", "pot2": "nak*xn"}, {"word": "nvlp-idwiki", "c_deletion": "nvlidwiki", "l_deletion": "nvpidwiki", "pot1": "nvl*idwiki", "pot2": "nvp*idwiki"}, {"word": "nvlp-v", "c_deletion": "nvlv", "l_deletion": "nvpv", "pot1": "nvl*v", "pot2": "nvp*v"}, {"word": "nvlp-vcikeSta", "c_deletion": "nvlvcikeSta", "l_deletion": "nvpvcikeSta", "pot1": "nvl*vcikeSta", "pot2": "nvp*vcikeSta"}, {"word": "nvlp-vciki", "c_deletion": "nvlvciki", "l_deletion": "nvpvciki", "pot1": "nvl*vciki", "pot2": "nvp*vciki"}, {"word": "nvlp-vciko", "c_deletion": "nvlvciko", "l_deletion": "nvpvciko", "pot1": "nvl*vciko", "pot2": "nvp*vciko"}, {"word": "nvlp-vcimyvn", "c_deletion": "nvlvcimyvn", "l_deletion": "nvpvcimyvn", "pot1": "nvl*vcimyvn", "pot2": "nvp*vcimyvn"}, {"word": "nvlp-vcimyvnsv", "c_deletion": "nvlvcimyvnsv", "l_deletion": "nvpvcimyvnsv", "pot1": "nvl*vcimyvnsv", "pot2": "nvp*vcimyvnsv"}, {"word": "nvlp-vcinxn", "c_deletion": "nvlvcinxn", "l_deletion": "nvpvcinxn", "pot1": "nvl*vcinxn", "pot2": "nvp*vcinxn"}, {"word": "nvlp-vcinxnkuna", "c_deletion": "nvlvcinxnkuna", "l_deletion": "nvpvcinxnkuna", "pot1": "nvl*vcinxnkuna", "pot2": "nvp*vcinxnkuna"}, {"word": "nvlp-vcil", "c_deletion": "nvlvcil", "l_deletion": "nvpvcil", "pot1": "nvl*vcil", "pot2": "nvp*vcil"}, {"word": "nvlp-vcilsulok", "c_deletion": "nvlvcilsulok", "l_deletion": "nvpvcilsulok", "pot1": "nvl*vcilsulok", "pot2": "nvp*vcilsulok"}, {"word": "nvlp-vcin", "c_deletion": "nvlvcin", "l_deletion": "nvpvcin", "pot1": "nvl*vcin", "pot2": "nvp*vcin"}, {"word": "nvlp-vcinta", "c_deletion": "nvlvcinta", "l_deletion": "nvpvcinta", "pot1": "nvl*vcinta", "pot2": "nvp*vcinta"}, {"word": "nvlp-vcintako", "c_deletion": "nvlvcintako", "l_deletion": "nvpvcintako", "pot1": "nvl*vcintako", "pot2": "nvp*vcintako"}, {"word": "nvlp-vcintanxn", "c_deletion": "nvlvcintanxn", "l_deletion": "nvpvcintanxn", "pot1": "nvl*vcintanxn", "pot2": "nvp*vcintanxn"}, {"word": "nvlp-vcyvSnxnte", "c_deletion": "nvlvcyvSnxnte", "l_deletion": "nvpvcyvSnxnte", "pot1": "nvl*vcyvSnxnte", "pot2": "nvp*vcyvSnxnte"}, {"word": "nvlp-vcyvSta", "c_deletion": "nvlvcyvSta", "l_deletion": "nvpvcyvSta", "pot1": "nvl*vcyvSta", "pot2": "nvp*vcyvSta"}, {"word": "nvlp-vcyvStako", "c_deletion": "nvlvcyvStako", "l_deletion": "nvpvcyvStako", "pot1": "nvl*vcyvStako", "pot2": "nvp*vcyvStako"}, {"word": "nvlp-vcyvSvyo", "c_deletion": "nvlvcyvSvyo", "l_deletion": "nvpvcyvSvyo", "pot1": "nvl*vcyvSvyo", "pot2": "nvp*vcyvSvyo"}, {"word": "nvlp-vcyvSxmyvn", "c_deletion": "nvlvcyvSxmyvn", "l_deletion": "nvpvcyvSxmyvn", "pot1": "nvl*vcyvSxmyvn", "pot2": "nvp*vcyvSxmyvn"}, {"word": "nvlp-vkaciko", "c_deletion": "nvlvkaciko", "l_deletion": "nvpvkaciko", "pot1": "nvl*vkaciko", "pot2": "nvp*vkaciko"}, {"word": "nvlp-vsv", "c_deletion": "nvlvsv", "l_deletion": "nvpvsv", "pot1": "nvl*vsv", "pot2": "nvp*vsv"}, {"word": "nvlp-vya", "c_deletion": "nvlvya", "l_deletion": "nvpvya", "pot1": "nvl*vya", "pot2": "nvp*vya"}, {"word": "nvlp-vyaci", "c_deletion": "nvlvyaci", "l_deletion": "nvpvyaci", "pot1": "nvl*vyaci", "pot2": "nvp*vyaci"}, {"word": "nvlp-vyo", "c_deletion": "nvlvyo", "l_deletion": "nvpvyo", "pot1": "nvl*vyo", "pot2": "nvp*vyo"}, {"word": "nvlp-vSci", "c_deletion": "nvlvSci", "l_deletion": "nvpvSci", "pot1": "nvl*vSci", "pot2": "nvp*vSci"}, {"word": "nvlp-vSko", "c_deletion": "nvlvSko", "l_deletion": "nvpvSko", "pot1": "nvl*vSko", "pot2": "nvp*vSko"}, {"word": "nvlp-vSnxnte", "c_deletion": "nvlvSnxnte", "l_deletion": "nvpvSnxnte", "pot1": "nvl*vSnxnte", "pot2": "nvp*vSnxnte"}, {"word": "nvlp-vSv", "c_deletion": "nvlvSv", "l_deletion": "nvpvSv", "pot1": "nvl*vSv", "pot2": "nvp*vSv"}, {"word": "nvlp-vSvsv", "c_deletion": "nvlvSvsv", "l_deletion": "nvpvSvsv", "pot1": "nvl*vSvsv", "pot2": "nvp*vSvsv"}, {"word": "nvlp-vSxmyvn", "c_deletion": "nvlvSxmyvn", "l_deletion": "nvpvSxmyvn", "pot1": "nvl*vSxmyvn", "pot2": "nvp*vSxmyvn"}, {"word": "nvlp-xmyvn", "c_deletion": "nvlxmyvn", "l_deletion": "nvpxmyvn", "pot1": "nvl*xmyvn", "pot2": "nvp*xmyvn"}, {"word": "nvlp-xniga", "c_deletion": "nvlxniga", "l_deletion": "nvpxniga", "pot1": "nvl*xniga", "pot2": "nvp*xniga"}, {"word": "nvlp-xnigan", "c_deletion": "nvlxnigan", "l_deletion": "nvpxnigan", "pot1": "nvl*xnigan", "pot2": "nvp*xnigan"}, {"word": "nvlp-xl", "c_deletion": "nvlxl", "l_deletion": "nvpxl", "pot1": "nvl*xl", "pot2": "nvp*xl"}, {"word": "nvlp-xmi", "c_deletion": "nvlxmi", "l_deletion": "nvpxmi", "pot1": "nvl*xmi", "pot2": "nvp*xmi"}, {"word": "nvlp-xn", "c_deletion": "nvlxn", "l_deletion": "nvpxn", "pot1": "nvl*xn", "pot2": "nvp*xn"}, {"word": "nvlp-xnte", "c_deletion": "nvlxnte", "l_deletion": "nvpxnte", "pot1": "nvl*xnte", "pot2": "nvp*xnte"}, {"word": "nvlp-xnteto", "c_deletion": "nvlxnteto", "l_deletion": "nvpxnteto", "pot1": "nvl*xnteto", "pot2": "nvp*xnteto"}, {"word": "nxlk-v", "c_deletion": "nxlv", "l_deletion": "nxkv", "pot1": "nxl*v", "pot2": "nxk*v"}, {"word": "nxlk-vci", "c_deletion": "nxlvci", "l_deletion": "nxkvci", "pot1": "nxl*vci", "pot2": "nxk*vci"}, {"word": "nxlk-vkacanhayo", "c_deletion": "nxlvkacanhayo", "l_deletion": "nxkvkacanhayo", "pot1": "nxl*vkacanhayo", "pot2": "nxk*vkacanhayo"}, {"word": "nxlk-vkaciko", "c_deletion": "nxlvkaciko", "l_deletion": "nxkvkaciko", "pot1": "nxl*vkaciko", "pot2": "nxk*vkaciko"}, {"word": "nxlk-vkako", "c_deletion": "nxlvkako", "l_deletion": "nxkvkako", "pot1": "nxl*vkako", "pot2": "nxk*vkako"}, {"word": "nxlk-vkamyvnsv", "c_deletion": "nxlvkamyvnsv", "l_deletion": "nxkvkamyvnsv", "pot1": "nxl*vkamyvnsv", "pot2": "nxk*vkamyvnsv"}, {"word": "nxlk-vkaniga", "c_deletion": "nxlvkaniga", "l_deletion": "nxkvkaniga", "pot1": "nxl*vkaniga", "pot2": "nxk*vkaniga"}, {"word": "nxlk-vkanxn", "c_deletion": "nxlvkanxn", "l_deletion": "nxkvkanxn", "pot1": "nxl*vkanxn", "pot2": "nxk*vkanxn"}, {"word": "nxlk-vkanxnkuna", "c_deletion": "nxlvkanxnkuna", "l_deletion": "nxkvkanxnkuna", "pot1": "nxl*vkanxnkuna", "pot2": "nxk*vkanxnkuna"}, {"word": "nxlk-vkanxnkunalanxn", "c_deletion": "nxlvkanxnkunalanxn", "l_deletion": "nxkvkanxnkunalanxn", "pot1": "nxl*vkanxnkunalanxn", "pot2": "nxk*vkanxnkunalanxn"}, {"word": "nxlk-vkasiko", "c_deletion": "nxlvkasiko", "l_deletion": "nxkvkasiko", "pot1": "nxl*vkasiko", "pot2": "nxk*vkasiko"}, {"word": "nxlk-vkata", "c_deletion": "nxlvkata", "l_deletion": "nxkvkata", "pot1": "nxl*vkata", "pot2": "nxk*vkata"}, {"word": "nxlk-vkacko", "c_deletion": "nxlvkacko", "l_deletion": "nxkvkacko", "pot1": "nxl*vkacko", "pot2": "nxk*vkacko"}, {"word": "nxlk-vkalgapwa", "c_deletion": "nxlvkalgapwa", "l_deletion": "nxkvkalgapwa", "pot1": "nxl*vkalgapwa", "pot2": "nxk*vkalgapwa"}, {"word": "nxlk-vkantanxn", "c_deletion": "nxlvkantanxn", "l_deletion": "nxkvkantanxn", "pot1": "nxl*vkantanxn", "pot2": "nxk*vkantanxn"}, {"word": "nxlk-vpvlimyvnxn", "c_deletion": "nxlvpvlimyvnxn", "l_deletion": "nxkvpvlimyvnxn", "pot1": "nxl*vpvlimyvnxn", "pot2": "nxk*vpvlimyvnxn"}, {"word": "nxlk-vsv", "c_deletion": "nxlvsv", "l_deletion": "nxkvsv", "pot1": "nxl*vsv", "pot2": "nxk*vsv"}, {"word": "nxlk-vsvgaci", "c_deletion": "nxlvsvgaci", "l_deletion": "nxkvsvgaci", "pot1": "nxl*vsvgaci", "pot2": "nxk*vsvgaci"}, {"word": "nxlk-vsvgacito", "c_deletion": "nxlvsvgacito", "l_deletion": "nxkvsvgacito", "pot1": "nxl*vsvgacito", "pot2": "nxk*vsvgacito"}, {"word": "nxlk-vsvnxn", "c_deletion": "nxlvsvnxn", "l_deletion": "nxkvsvnxn", "pot1": "nxl*vsvnxn", "pot2": "nxk*vsvnxn"}, {"word": "nxlk-vsvto", "c_deletion": "nxlvsvto", "l_deletion": "nxkvsvto", "pot1": "nxl*vsvto", "pot2": "nxk*vsvto"}, {"word": "nxlk-vto", "c_deletion": "nxlvto", "l_deletion": "nxkvto", "pot1": "nxl*vto", "pot2": "nxk*vto"}, {"word": "nxlk-vS", "c_deletion": "nxlvS", "l_deletion": "nxkvS", "pot1": "nxl*vS", "pot2": "nxk*vS"}, {"word": "nxlk-vSciman", "c_deletion": "nxlvSciman", "l_deletion": "nxkvSciman", "pot1": "nxl*vSciman", "pot2": "nxk*vSciman"}, {"word": "nxlk-vScyo", "c_deletion": "nxlvScyo", "l_deletion": "nxkvScyo", "pot1": "nxl*vScyo", "pot2": "nxk*vScyo"}, {"word": "nxlk-vSkuna", "c_deletion": "nxlvSkuna", "l_deletion": "nxkvSkuna", "pot1": "nxl*vSkuna", "pot2": "nxk*vSkuna"}, {"word": "nxlk-vSna", "c_deletion": "nxlvSna", "l_deletion": "nxkvSna", "pot1": "nxl*vSna", "pot2": "nxk*vSna"}, {"word": "nxlk-vSta", "c_deletion": "nxlvSta", "l_deletion": "nxkvSta", "pot1": "nxl*vSta", "pot2": "nxk*vSta"}, {"word": "nxlk-vStako", "c_deletion": "nxlvStako", "l_deletion": "nxkvStako", "pot1": "nxl*vStako", "pot2": "nxk*vStako"}, {"word": "nxlk-vStalanxn", "c_deletion": "nxlvStalanxn", "l_deletion": "nxkvStalanxn", "pot1": "nxl*vStalanxn", "pot2": "nxk*vStalanxn"}, {"word": "nxlk-vStvlakoyo", "c_deletion": "nxlvStvlakoyo", "l_deletion": "nxkvStvlakoyo", "pot1": "nxl*vStvlakoyo", "pot2": "nxk*vStvlakoyo"}, {"word": "nxlk-vSvyo", "c_deletion": "nxlvSvyo", "l_deletion": "nxkvSvyo", "pot1": "nxl*vSvyo", "pot2": "nxk*vSvyo"}, {"word": "nxlk-vSxniga", "c_deletion": "nxlvSxniga", "l_deletion": "nxkvSxniga", "pot1": "nxl*vSxniga", "pot2": "nxk*vSxniga"}, {"word": "nxlk-vSxl", "c_deletion": "nxlvSxl", "l_deletion": "nxkvSxl", "pot1": "nxl*vSxl", "pot2": "nxk*vSxl"}, {"word": "nxlk-xmyvn", "c_deletion": "nxlxmyvn", "l_deletion": "nxkxmyvn", "pot1": "nxl*xmyvn", "pot2": "nxk*xmyvn"}, {"word": "nxlk-xmyvnxn", "c_deletion": "nxlxmyvnxn", "l_deletion": "nxkxmyvnxn", "pot1": "nxl*xmyvnxn", "pot2": "nxk*xmyvnxn"}, {"word": "nxlk-xsyvSnxnte", "c_deletion": "nxlxsyvSnxnte", "l_deletion": "nxkxsyvSnxnte", "pot1": "nxl*xsyvSnxnte", "pot2": "nxk*xsyvSnxnte"}, {"word": "nxlk-xl", "c_deletion": "nxlxl", "l_deletion": "nxkxl", "pot1": "nxl*xl", "pot2": "nxk*xl"}, {"word": "nxlk-xn", "c_deletion": "nxlxn", "l_deletion": "nxkxn", "pot1": "nxl*xn", "pot2": "nxk*xn"}, {"word": "nxlk-xni", "c_deletion": "nxlxni", "l_deletion": "nxkxni", "pot1": "nxl*xni", "pot2": "nxk*xni"}, {"word": "olk-amesinxn", "c_deletion": "olamesinxn", "l_deletion": "okamesinxn", "pot1": "ol*amesinxn", "pot2": "ok*amesinxn"}, {"word": "olk-ameya", "c_deletion": "olameya", "l_deletion": "okameya", "pot1": "ol*ameya", "pot2": "ok*ameya"}, {"word": "olm-a", "c_deletion": "ola", "l_deletion": "oma", "pot1": "ol*a", "pot2": "om*a"}, {"word": "olm-akal", "c_deletion": "olakal", "l_deletion": "omakal", "pot1": "ol*akal", "pot2": "om*akal"}, {"word": "olm-awasv", "c_deletion": "olawasv", "l_deletion": "omawasv", "pot1": "ol*awasv", "pot2": "om*awasv"}, {"word": "olm-xl", "c_deletion": "olxl", "l_deletion": "omxl", "pot1": "ol*xl", "pot2": "om*xl"}, {"word": "palk-a", "c_deletion": "pala", "l_deletion": "paka", "pot1": "pal*a", "pot2": "pak*a"}, {"word": "palk-aciko", "c_deletion": "palaciko", "l_deletion": "pakaciko", "pot1": "pal*aciko", "pot2": "pak*aciko"}, {"word": "palk-acilyvko", "c_deletion": "palacilyvko", "l_deletion": "pakacilyvko", "pot1": "pal*acilyvko", "pot2": "pak*acilyvko"}, {"word": "palk-acimyvnsv", "c_deletion": "palacimyvnsv", "l_deletion": "pakacimyvnsv", "pot1": "pal*acimyvnsv", "pot2": "pak*acimyvnsv"}, {"word": "palk-acinxn", "c_deletion": "palacinxn", "l_deletion": "pakacinxn", "pot1": "pal*acinxn", "pot2": "pak*acinxn"}, {"word": "palk-acisin", "c_deletion": "palacisin", "l_deletion": "pakacisin", "pot1": "pal*acisin", "pot2": "pak*acisin"}, {"word": "palk-acin", "c_deletion": "palacin", "l_deletion": "pakacin", "pot1": "pal*acin", "pot2": "pak*acin"}, {"word": "palk-acyvSko", "c_deletion": "palacyvSko", "l_deletion": "pakacyvSko", "pot1": "pal*acyvSko", "pot2": "pak*acyvSko"}, {"word": "palk-acyvStako", "c_deletion": "palacyvStako", "l_deletion": "pakacyvStako", "pot1": "pal*acyvStako", "pot2": "pak*acyvStako"}, {"word": "palk-acyvStatxnka", "c_deletion": "palacyvStatxnka", "l_deletion": "pakacyvStatxnka", "pot1": "pal*acyvStatxnka", "pot2": "pak*acyvStatxnka"}, {"word": "palk-acyvStvla", "c_deletion": "palacyvStvla", "l_deletion": "pakacyvStvla", "pot1": "pal*acyvStvla", "pot2": "pak*acyvStvla"}, {"word": "palk-acyvStxnte", "c_deletion": "palacyvStxnte", "l_deletion": "pakacyvStxnte", "pot1": "pal*acyvStxnte", "pot2": "pak*acyvStxnte"}, {"word": "palk-akaciko", "c_deletion": "palakaciko", "l_deletion": "pakakaciko", "pot1": "pal*akaciko", "pot2": "pak*akaciko"}, {"word": "palk-asv", "c_deletion": "palasv", "l_deletion": "pakasv", "pot1": "pal*asv", "pot2": "pak*asv"}, {"word": "palk-ayo", "c_deletion": "palayo", "l_deletion": "pakayo", "pot1": "pal*ayo", "pot2": "pak*ayo"}, {"word": "palk-aStaka", "c_deletion": "palaStaka", "l_deletion": "pakaStaka", "pot1": "pal*aStaka", "pot2": "pak*aStaka"}, {"word": "palk-xmyvnsv", "c_deletion": "palxmyvnsv", "l_deletion": "pakxmyvnsv", "pot1": "pal*xmyvnsv", "pot2": "pak*xmyvnsv"}, {"word": "palk-xniga", "c_deletion": "palxniga", "l_deletion": "pakxniga", "pot1": "pal*xniga", "pot2": "pak*xniga"}, {"word": "palk-xmi", "c_deletion": "palxmi", "l_deletion": "pakxmi", "pot1": "pal*xmi", "pot2": "pak*xmi"}, {"word": "palk-xmilako", "c_deletion": "palxmilako", "l_deletion": "pakxmilako", "pot1": "pal*xmilako", "pot2": "pak*xmilako"}, {"word": "palk-xmxl", "c_deletion": "palxmxl", "l_deletion": "pakxmxl", "pot1": "pal*xmxl", "pot2": "pak*xmxl"}, {"word": "palk-xn", "c_deletion": "palxn", "l_deletion": "pakxn", "pot1": "pal*xn", "pot2": "pak*xn"}, {"word": "palk-xnte", "c_deletion": "palxnte", "l_deletion": "pakxnte", "pot1": "pal*xnte", "pot2": "pak*xnte"}, {"word": "palp-a", "c_deletion": "pala", "l_deletion": "papa", "pot1": "pal*a", "pot2": "pap*a"}, {"word": "palp-akaciko", "c_deletion": "palakaciko", "l_deletion": "papakaciko", "pot1": "pal*akaciko", "pot2": "pap*akaciko"}, {"word": "palp-akamyvnsv", "c_deletion": "palakamyvnsv", "l_deletion": "papakamyvnsv", "pot1": "pal*akamyvnsv", "pot2": "pap*akamyvnsv"}, {"word": "palp-anakaya", "c_deletion": "palanakaya", "l_deletion": "papanakaya", "pot1": "pal*anakaya", "pot2": "pap*anakaya"}, {"word": "palp-apoko", "c_deletion": "palapoko", "l_deletion": "papapoko", "pot1": "pal*apoko", "pot2": "pap*apoko"}, {"word": "palp-asv", "c_deletion": "palasv", "l_deletion": "papasv", "pot1": "pal*asv", "pot2": "pap*asv"}, {"word": "palp-ato", "c_deletion": "palato", "l_deletion": "papato", "pot1": "pal*ato", "pot2": "pap*ato"}, {"word": "palp-aya", "c_deletion": "palaya", "l_deletion": "papaya", "pot1": "pal*aya", "pot2": "pap*aya"}, {"word": "palp-aSnxnte", "c_deletion": "palaSnxnte", "l_deletion": "papaSnxnte", "pot1": "pal*aSnxnte", "pot2": "pap*aSnxnte"}, {"word": "palp-aStako", "c_deletion": "palaStako", "l_deletion": "papaStako", "pot1": "pal*aStako", "pot2": "pap*aStako"}, {"word": "palp-aStvn", "c_deletion": "palaStvn", "l_deletion": "papaStvn", "pot1": "pal*aStvn", "pot2": "pap*aStvn"}, {"word": "palp-aSxl", "c_deletion": "palaSxl", "l_deletion": "papaSxl", "pot1": "pal*aSxl", "pot2": "pap*aSxl"}, {"word": "palp-xlyvko", "c_deletion": "palxlyvko", "l_deletion": "papxlyvko", "pot1": "pal*xlyvko", "pot2": "pap*xlyvko"}, {"word": "palp-xmyvn", "c_deletion": "palxmyvn", "l_deletion": "papxmyvn", "pot1": "pal*xmyvn", "pot2": "pap*xmyvn"}, {"word": "palp-xmyvnsv", "c_deletion": "palxmyvnsv", "l_deletion": "papxmyvnsv", "pot1": "pal*xmyvnsv", "pot2": "pap*xmyvnsv"}, {"word": "palp-xmyvnxn", "c_deletion": "palxmyvnxn", "l_deletion": "papxmyvnxn", "pot1": "pal*xmyvnxn", "pot2": "pap*xmyvnxn"}, {"word": "palp-xsyvkaciko", "c_deletion": "palxsyvkaciko", "l_deletion": "papxsyvkaciko", "pot1": "pal*xsyvkaciko", "pot2": "pap*xsyvkaciko"}, {"word": "palp-xl", "c_deletion": "palxl", "l_deletion": "papxl", "pot1": "pal*xl", "pot2": "pap*xl"}, {"word": "palp-xn", "c_deletion": "palxn", "l_deletion": "papxn", "pot1": "pal*xn", "pot2": "pap*xn"}, {"word": "pulk-xn", "c_deletion": "pulxn", "l_deletion": "pukxn", "pot1": "pul*xn", "pot2": "puk*xn"}, {"word": "pulk-xnsek", "c_deletion": "pulxnsek", "l_deletion": "pukxnsek", "pot1": "pul*xnsek", "pot2": "puk*xnsek"}, {"word": "pulk-xnsekkwa", "c_deletion": "pulxnsekkwa", "l_deletion": "pukxnsekkwa", "pot1": "pul*xnsekkwa", "pot2": "puk*xnsekkwa"}, {"word": "salm-a", "c_deletion": "sala", "l_deletion": "sama", "pot1": "sal*a", "pot2": "sam*a"}, {"word": "salm-acimyvn", "c_deletion": "salacimyvn", "l_deletion": "samacimyvn", "pot1": "sal*acimyvn", "pot2": "sam*acimyvn"}, {"word": "salm-acukvna", "c_deletion": "salacukvna", "l_deletion": "samacukvna", "pot1": "sal*acukvna", "pot2": "sam*acukvna"}, {"word": "salm-akaciko", "c_deletion": "salakaciko", "l_deletion": "samakaciko", "pot1": "sal*akaciko", "pot2": "sam*akaciko"}, {"word": "salm-akatxnka", "c_deletion": "salakatxnka", "l_deletion": "samakatxnka", "pot1": "sal*akatxnka", "pot2": "sam*akatxnka"}, {"word": "salm-akacko", "c_deletion": "salakacko", "l_deletion": "samakacko", "pot1": "sal*akacko", "pot2": "sam*akacko"}, {"word": "salm-amvkko", "c_deletion": "salamvkko", "l_deletion": "samamvkko", "pot1": "sal*amvkko", "pot2": "sam*amvkko"}, {"word": "salm-anohxn", "c_deletion": "salanohxn", "l_deletion": "samanohxn", "pot1": "sal*anohxn", "pot2": "sam*anohxn"}, {"word": "salm-anwaSv", "c_deletion": "salanwaSv", "l_deletion": "samanwaSv", "pot1": "sal*anwaSv", "pot2": "sam*anwaSv"}, {"word": "salm-asv", "c_deletion": "salasv", "l_deletion": "samasv", "pot1": "sal*asv", "pot2": "sam*asv"}, {"word": "salm-asvto", "c_deletion": "salasvto", "l_deletion": "samasvto", "pot1": "sal*asvto", "pot2": "sam*asvto"}, {"word": "salm-ato", "c_deletion": "salato", "l_deletion": "samato", "pot1": "sal*ato", "pot2": "sam*ato"}, {"word": "salm-aya", "c_deletion": "salaya", "l_deletion": "samaya", "pot1": "sal*aya", "pot2": "sam*aya"}, {"word": "salm-v", "c_deletion": "salv", "l_deletion": "samv", "pot1": "sal*v", "pot2": "sam*v"}, {"word": "salm-x", "c_deletion": "salx", "l_deletion": "samx", "pot1": "sal*x", "pot2": "sam*x"}, {"word": "salm-xla", "c_deletion": "salxla", "l_deletion": "samxla", "pot1": "sal*xla", "pot2": "sam*xla"}, {"word": "salm-xlako", "c_deletion": "salxlako", "l_deletion": "samxlako", "pot1": "sal*xlako", "pot2": "sam*xlako"}, {"word": "salm-xloSv", "c_deletion": "salxloSv", "l_deletion": "samxloSv", "pot1": "sal*xloSv", "pot2": "sam*xloSv"}, {"word": "salm-xmyvn", "c_deletion": "salxmyvn", "l_deletion": "samxmyvn", "pot1": "sal*xmyvn", "pot2": "sam*xmyvn"}, {"word": "salm-xmyvnxn", "c_deletion": "salxmyvnxn", "l_deletion": "samxmyvnxn", "pot1": "sal*xmyvnxn", "pot2": "sam*xmyvnxn"}, {"word": "salm-xsyvkacko", "c_deletion": "salxsyvkacko", "l_deletion": "samxsyvkacko", "pot1": "sal*xsyvkacko", "pot2": "sam*xsyvkacko"}, {"word": "salm-xsyvStamyvnxn", "c_deletion": "salxsyvStamyvnxn", "l_deletion": "samxsyvStamyvnxn", "pot1": "sal*xsyvStamyvnxn", "pot2": "sam*xsyvStamyvnxn"}, {"word": "salm-xn", "c_deletion": "salxn", "l_deletion": "samxn", "pot1": "sal*xn", "pot2": "sam*xn"}, {"word": "talm-a", "c_deletion": "tala", "l_deletion": "tama", "pot1": "tal*a", "pot2": "tam*a"}, {"word": "talm-acyvStanxn", "c_deletion": "talacyvStanxn", "l_deletion": "tamacyvStanxn", "pot1": "tal*acyvStanxn", "pot2": "tam*acyvStanxn"}, {"word": "talm-aiSko", "c_deletion": "talaiSko", "l_deletion": "tamaiSko", "pot1": "tal*aiSko", "pot2": "tam*aiSko"}, {"word": "talm-aiStako", "c_deletion": "talaiStako", "l_deletion": "tamaiStako", "pot1": "tal*aiStako", "pot2": "tam*aiStako"}, {"word": "talm-akaci", "c_deletion": "talakaci", "l_deletion": "tamakaci", "pot1": "tal*akaci", "pot2": "tam*akaci"}, {"word": "talm-akaciko", "c_deletion": "talakaciko", "l_deletion": "tamakaciko", "pot1": "tal*akaciko", "pot2": "tam*akaciko"}, {"word": "talm-akacimanxn", "c_deletion": "talakacimanxn", "l_deletion": "tamakacimanxn", "pot1": "tal*akacimanxn", "pot2": "tam*akacimanxn"}, {"word": "talm-akakin", "c_deletion": "talakakin", "l_deletion": "tamakakin", "pot1": "tal*akakin", "pot2": "tam*akakin"}, {"word": "talm-akako", "c_deletion": "talakako", "l_deletion": "tamakako", "pot1": "tal*akako", "pot2": "tam*akako"}, {"word": "talm-akalyvko", "c_deletion": "talakalyvko", "l_deletion": "tamakalyvko", "pot1": "tal*akalyvko", "pot2": "tam*akalyvko"}, {"word": "talm-akanxn", "c_deletion": "talakanxn", "l_deletion": "tamakanxn", "pot1": "tal*akanxn", "pot2": "tam*akanxn"}, {"word": "talm-akasv", "c_deletion": "talakasv", "l_deletion": "tamakasv", "pot1": "tal*akasv", "pot2": "tam*akasv"}, {"word": "talm-akatvlakoyo", "c_deletion": "talakatvlakoyo", "l_deletion": "tamakatvlakoyo", "pot1": "tal*akatvlakoyo", "pot2": "tam*akatvlakoyo"}, {"word": "talm-akal", "c_deletion": "talakal", "l_deletion": "tamakal", "pot1": "tal*akal", "pot2": "tam*akal"}, {"word": "talm-akan", "c_deletion": "talakan", "l_deletion": "tamakan", "pot1": "tal*akan", "pot2": "tam*akan"}, {"word": "talm-akantako", "c_deletion": "talakantako", "l_deletion": "tamakantako", "pot1": "tal*akantako", "pot2": "tam*akantako"}, {"word": "talm-akantalanxn", "c_deletion": "talakantalanxn", "l_deletion": "tamakantalanxn", "pot1": "tal*akantalanxn", "pot2": "tam*akantalanxn"}, {"word": "talm-akantanxn", "c_deletion": "talakantanxn", "l_deletion": "tamakantanxn", "pot1": "tal*akantanxn", "pot2": "tam*akantanxn"}, {"word": "talm-asv", "c_deletion": "talasv", "l_deletion": "tamasv", "pot1": "tal*asv", "pot2": "tam*asv"}, {"word": "talm-aS", "c_deletion": "talaS", "l_deletion": "tamaS", "pot1": "tal*aS", "pot2": "tam*aS"}, {"word": "talm-aScimanxn", "c_deletion": "talaScimanxn", "l_deletion": "tamaScimanxn", "pot1": "tal*aScimanxn", "pot2": "tam*aScimanxn"}, {"word": "talm-aSkeScyo", "c_deletion": "talaSkeScyo", "l_deletion": "tamaSkeScyo", "pot1": "tal*aSkeScyo", "pot2": "tam*aSkeScyo"}, {"word": "talm-aSko", "c_deletion": "talaSko", "l_deletion": "tamaSko", "pot1": "tal*aSko", "pot2": "tam*aSko"}, {"word": "talm-aSkuna", "c_deletion": "talaSkuna", "l_deletion": "tamaSkuna", "pot1": "tal*aSkuna", "pot2": "tam*aSkuna"}, {"word": "talm-aSkvtxnyo", "c_deletion": "talaSkvtxnyo", "l_deletion": "tamaSkvtxnyo", "pot1": "tal*aSkvtxnyo", "pot2": "tam*aSkvtxnyo"}, {"word": "talm-aSna", "c_deletion": "talaSna", "l_deletion": "tamaSna", "pot1": "tal*aSna", "pot2": "tam*aSna"}, {"word": "talm-aSnayo", "c_deletion": "talaSnayo", "l_deletion": "tamaSnayo", "pot1": "tal*aSnayo", "pot2": "tam*aSnayo"}, {"word": "talm-aSne", "c_deletion": "talaSne", "l_deletion": "tamaSne", "pot1": "tal*aSne", "pot2": "tam*aSne"}, {"word": "talm-aSnelan", "c_deletion": "talaSnelan", "l_deletion": "tamaSnelan", "pot1": "tal*aSnelan", "pot2": "tam*aSnelan"}, {"word": "talm-aSnxnci", "c_deletion": "talaSnxnci", "l_deletion": "tamaSnxnci", "pot1": "tal*aSnxnci", "pot2": "tam*aSnxnci"}, {"word": "talm-aSnxncinxn", "c_deletion": "talaSnxncinxn", "l_deletion": "tamaSnxncinxn", "pot1": "tal*aSnxncinxn", "pot2": "tam*aSnxncinxn"}, {"word": "talm-aSnxnte", "c_deletion": "talaSnxnte", "l_deletion": "tamaSnxnte", "pot1": "tal*aSnxnte", "pot2": "tam*aSnxnte"}, {"word": "talm-aSnxnteyo", "c_deletion": "talaSnxnteyo", "l_deletion": "tamaSnxnteyo", "pot1": "tal*aSnxnteyo", "pot2": "tam*aSnxnteyo"}, {"word": "talm-aSnya", "c_deletion": "talaSnya", "l_deletion": "tamaSnya", "pot1": "tal*aSnya", "pot2": "tam*aSnya"}, {"word": "talm-aSsxpniga", "c_deletion": "talaSsxpniga", "l_deletion": "tamaSsxpniga", "pot1": "tal*aSsxpniga", "pot2": "tam*aSsxpniga"}, {"word": "talm-aSsxpnita", "c_deletion": "talaSsxpnita", "l_deletion": "tamaSsxpnita", "pot1": "tal*aSsxpnita", "pot2": "tam*aSsxpnita"}, {"word": "talm-aSta", "c_deletion": "talaSta", "l_deletion": "tamaSta", "pot1": "tal*aSta", "pot2": "tam*aSta"}, {"word": "talm-aStaka", "c_deletion": "talaStaka", "l_deletion": "tamaStaka", "pot1": "tal*aStaka", "pot2": "tam*aStaka"}, {"word": "talm-aStako", "c_deletion": "talaStako", "l_deletion": "tamaStako", "pot1": "tal*aStako", "pot2": "tam*aStako"}, {"word": "talm-aStakoto", "c_deletion": "talaStakoto", "l_deletion": "tamaStakoto", "pot1": "tal*aStakoto", "pot2": "tam*aStakoto"}, {"word": "talm-aStalako", "c_deletion": "talaStalako", "l_deletion": "tamaStalako", "pot1": "tal*aStalako", "pot2": "tam*aStalako"}, {"word": "talm-aStalanxn", "c_deletion": "talaStalanxn", "l_deletion": "tamaStalanxn", "pot1": "tal*aStalanxn", "pot2": "tam*aStalanxn"}, {"word": "talm-aStanxn", "c_deletion": "talaStanxn", "l_deletion": "tamaStanxn", "pot1": "tal*aStanxn", "pot2": "tam*aStanxn"}, {"word": "talm-aStan", "c_deletion": "talaStan", "l_deletion": "tamaStan", "pot1": "tal*aStan", "pot2": "tam*aStan"}, {"word": "talm-aSteyo", "c_deletion": "talaSteyo", "l_deletion": "tamaSteyo", "pot1": "tal*aSteyo", "pot2": "tam*aSteyo"}, {"word": "talm-aStvla", "c_deletion": "talaStvla", "l_deletion": "tamaStvla", "pot1": "tal*aStvla", "pot2": "tam*aStvla"}, {"word": "talm-aSv", "c_deletion": "talaSv", "l_deletion": "tamaSv", "pot1": "tal*aSv", "pot2": "tam*aSv"}, {"word": "talm-aSvyo", "c_deletion": "talaSvyo", "l_deletion": "tamaSvyo", "pot1": "tal*aSvyo", "pot2": "tam*aSvyo"}, {"word": "talm-aSxmyvn", "c_deletion": "talaSxmyvn", "l_deletion": "tamaSxmyvn", "pot1": "tal*aSxmyvn", "pot2": "tam*aSxmyvn"}, {"word": "talm-aSxniga", "c_deletion": "talaSxniga", "l_deletion": "tamaSxniga", "pot1": "tal*aSxniga", "pot2": "tam*aSxniga"}, {"word": "talm-aSxlga", "c_deletion": "talaSxlga", "l_deletion": "tamaSxlga", "pot1": "tal*aSxlga", "pot2": "tam*aSxlga"}, {"word": "talm-aSxm", "c_deletion": "talaSxm", "l_deletion": "tamaSxm", "pot1": "tal*aSxm", "pot2": "tam*aSxm"}, {"word": "talm-v", "c_deletion": "talv", "l_deletion": "tamv", "pot1": "tal*v", "pot2": "tam*v"}, {"word": "talm-xkin", "c_deletion": "talxkin", "l_deletion": "tamxkin", "pot1": "tal*xkin", "pot2": "tam*xkin"}, {"word": "talm-xla", "c_deletion": "talxla", "l_deletion": "tamxla", "pot1": "tal*xla", "pot2": "tam*xla"}, {"word": "talm-xlyvko", "c_deletion": "talxlyvko", "l_deletion": "tamxlyvko", "pot1": "tal*xlyvko", "pot2": "tam*xlyvko"}, {"word": "talm-xniga", "c_deletion": "talxniga", "l_deletion": "tamxniga", "pot1": "tal*xniga", "pot2": "tam*xniga"}, {"word": "talm-xsin", "c_deletion": "talxsin", "l_deletion": "tamxsin", "pot1": "tal*xsin", "pot2": "tam*xsin"}, {"word": "talm-xsyvsv", "c_deletion": "talxsyvsv", "l_deletion": "tamxsyvsv", "pot1": "tal*xsyvsv", "pot2": "tam*xsyvsv"}, {"word": "talm-xsyvSnayo", "c_deletion": "talxsyvSnayo", "l_deletion": "tamxsyvSnayo", "pot1": "tal*xsyvSnayo", "pot2": "tam*xsyvSnayo"}, {"word": "talm-xsyvSta", "c_deletion": "talxsyvSta", "l_deletion": "tamxsyvSta", "pot1": "tal*xsyvSta", "pot2": "tam*xsyvSta"}, {"word": "talm-xsyvSvyo", "c_deletion": "talxsyvSvyo", "l_deletion": "tamxsyvSvyo", "pot1": "tal*xsyvSvyo", "pot2": "tam*xsyvSvyo"}, {"word": "talm-xlga", "c_deletion": "talxlga", "l_deletion": "tamxlga", "pot1": "tal*xlga", "pot2": "tam*xlga"}, {"word": "talm-xm", "c_deletion": "talxm", "l_deletion": "tamxm", "pot1": "tal*xm", "pot2": "tam*xm"}, {"word": "talm-xn", "c_deletion": "talxn", "l_deletion": "tamxn", "pot1": "tal*xn", "pot2": "tam*xn"}, {"word": "txnvlp-xn", "c_deletion": "txnvlxn", "l_deletion": "txnvpxn", "pot1": "txnvl*xn", "pot2": "txnvp*xn"}, {"word": "xlP-vnohko", "c_deletion": "xlvnohko", "l_deletion": "xPvnohko", "pot1": "xl*vnohko", "pot2": "xP*vnohko"}, {"word": "xlP-vpolako", "c_deletion": "xlvpolako", "l_deletion": "xPvpolako", "pot1": "xl*vpolako", "pot2": "xP*vpolako"}, {"word": "xlP-xmyvnsv", "c_deletion": "xlxmyvnsv", "l_deletion": "xPxmyvnsv", "pot1": "xl*xmyvnsv", "pot2": "xP*xmyvnsv"}, {"word": "yalp-a", "c_deletion": "yala", "l_deletion": "yapa", "pot1": "yal*a", "pot2": "yap*a"}, {"word": "yalp-aciciman", "c_deletion": "yalaciciman", "l_deletion": "yapaciciman", "pot1": "yal*aciciman", "pot2": "yap*aciciman"}, {"word": "yalp-acinigan", "c_deletion": "yalacinigan", "l_deletion": "yapacinigan", "pot1": "yal*acinigan", "pot2": "yap*acinigan"}, {"word": "yalp-asv", "c_deletion": "yalasv", "l_deletion": "yapasv", "pot1": "yal*asv", "pot2": "yap*asv"}, {"word": "yalp-ayo", "c_deletion": "yalayo", "l_deletion": "yapayo", "pot1": "yal*ayo", "pot2": "yap*ayo"}, {"word": "yalp-aSko", "c_deletion": "yalaSko", "l_deletion": "yapaSko", "pot1": "yal*aSko", "pot2": "yap*aSko"}, {"word": "yalp-xn", "c_deletion": "yalxn", "l_deletion": "yapxn", "pot1": "yal*xn", "pot2": "yap*xn"}, {"word": "yalp-xnka", "c_deletion": "yalxnka", "l_deletion": "yapxnka", "pot1": "yal*xnka", "pot2": "yap*xnka"}]